{
	"__comment": "Designed by Tacocat with Cubik Studio - https://cubik.studio",
	"ambientocclusion": false,
	"textures": {
		"texture": "painting/moving_paintings/medieval_standing_group65",
		"texture1": "painting/dutch_man_frame",
		"particle": "painting/dutch_man_frame"
	},
	"elements": [ 	 
		{
			"__comment": "Element",
			"from": [ -1.5, 0, 15.5 ],
			"to": [ 17.83333, 15.66667, 15.501 ],
			"faces": {
				"north": { "uv": [ 4, 2.75, 11.25, 12.625 ], "texture": "#texture", "rotation": 270 },
				"south": { "uv": [ 4, 2.5, 12, 14.125 ], "texture": "#texture", "rotation": 270 },
				"west": { "uv": [ 9.33333, 0, 9.33433, 16 ], "texture": "#texture" },
				"east": { "uv": [ 6.66567, 0, 6.66667, 16 ], "texture": "#texture" }
			}
		},
		{
			"__comment": "Element",
			"from": [ -2.5001, 2.3333, 14.8344 ],
			"to": [ -0.8334301, 14.66663, 15.50107 ],
			"faces": {
				"down": { "uv": [ 1.4, 1.4, 2.4, 15.4 ], "texture": "#texture1" },
				"up": { "uv": [ 1.4, 1.4, 2.4, 15.4 ], "texture": "#texture1" },
				"north": { "uv": [ 1.4, 7.4, 2.4, 14.2 ], "texture": "#texture1" },
				"south": { "uv": [ 1.4, 1.4, 2.4, 15.4 ], "texture": "#texture1" },
				"west": { "uv": [ 0.4, 0, 0, 14 ], "texture": "#texture1" },
				"east": { "uv": [ 0, 0, 0.4, 14 ], "texture": "#texture1" }
			}
		},
		{
			"__comment": "Element",
			"from": [ 17.1666, 2.3333, 14.8343 ],
			"to": [ 18.83327, 14.66663, 15.50097 ],
			"faces": {
				"up": { "uv": [ 0.4, 1.2, 1.4, 15.4 ], "texture": "#texture1" },
				"north": { "uv": [ 0.4, 1.2, 1.4, 8.2 ], "texture": "#texture1" },
				"south": { "uv": [ 0.4, 1.2, 1.4, 15.4 ], "texture": "#texture1" },
				"west": { "uv": [ 0.4, 0, 0, 14 ], "texture": "#texture1" },
				"east": { "uv": [ 0, 0, 0.4, 14 ], "texture": "#texture1" }
			}
		},
		{
			"__comment": "Element",
			"from": [ -2.5, 0, 14.8343 ],
			"to": [ 18.83333, 2.33333, 15.50097 ],
			"faces": {
				"down": { "uv": [ 2.4, 2.4, 15, 2.8 ], "texture": "#texture1" },
				"up": { "uv": [ 2.4, 2.4, 15, 2.8 ], "texture": "#texture1" },
				"north": { "uv": [ 2.4, 1.4, 15, 2.8 ], "texture": "#texture1" },
				"south": { "uv": [ 2.4, 1.4, 15, 2.8 ], "texture": "#texture1" },
				"west": { "uv": [ 0.4, 12.6, 0, 14 ], "texture": "#texture1" },
				"east": { "uv": [ 0, 12.6, 0.4, 14 ], "texture": "#texture1" }
			}
		},
		{
			"__comment": "Element",
			"from": [ -2.5, 14.6667, 14.8343 ],
			"to": [ 18.83333, 17.00003, 15.50097 ],
			"faces": {
				"down": { "uv": [ 0.4, 0, 13, 0.3999996 ], "texture": "#texture1", "rotation": 180 },
				"up": { "uv": [ 13, 0, 0.3999996, 0.3999996 ], "texture": "#texture1" },
				"north": { "uv": [ 0.4, 0, 13, 1.4 ], "texture": "#texture1" },
				"south": { "uv": [ 0.4, 0, 13, 1.4 ], "texture": "#texture1" },
				"west": { "uv": [ 0.4, 0, 0, 1.4 ], "texture": "#texture1" },
				"east": { "uv": [ 0, 0, 0.4, 1.4 ], "texture": "#texture1" }
			}
		}
	],
	"display": {
		"fixed": {
			"rotation":  [ 0, 180, 0.3 ],
			"translation":  [ 0, 6, -14.1 ],
			"scale":  [ 2, 2, 2 ]
		}
	}
}