{
	"__comment": "Designed by Tacocat with Cubik Studio - https://cubik.studio",
	"textures": {
		"particle": "block/acacia_trapdoor",
		"texture": "block/acacia_trapdoor"
	},
	"elements": [ 	 
		{
			"__comment": "Box15",
			"from": [ 0, 0, 0 ],
			"to": [ 16, 16, 16 ],
			"faces": {
				"down": { "uv": [ 0, 0, 16, 16 ], "texture": "#texture" },
				"up": { "uv": [ 0, 0, 16, 16 ], "texture": "#texture" },
				"north": { "uv": [ 0, 0, 16, 16 ], "texture": "#texture" },
				"south": { "uv": [ 0, 0, 16, 16 ], "texture": "#texture" },
				"west": { "uv": [ 0, 0, 16, 16 ], "texture": "#texture" },
				"east": { "uv": [ 0, 0, 16, 16 ], "texture": "#texture" }
			}
		}
	],
	"display": {
		"firstperson_righthand": {
			"rotation":  [ 66, 13, 9 ],
			"translation":  [ 1, -1, 5 ]
		},
		"gui": {
			"rotation":  [ 90, 0, 0 ],
			"translation":  [ 0, -6, 0 ]
		},
		"fixed": {
			"rotation":  [ 90, 0, -180 ],
			"translation":  [ -4, -18, -6 ],
			"scale":  [ 3, 1, 3 ]
		}
	}
}