{
	"parent": "item/handheld",
	"textures": {
		"layer0": "item/diamond_sword"
	},
	"overrides": [
		{ "predicate": {"damaged": 0, "damage": 0},                       "model": "item/diamond_sword"},
		{ "predicate": {"damaged": 0, "damage": 0.8124199743918054},      "model": "custom/dumbledore/dumbledorechair_90"},
		{ "predicate": {"damaged": 0, "damage": 0.8130601792573623},      "model": "custom/ford_anglia/windows"},
		{ "predicate": {"damaged": 0, "damage": 0.8137003841229193},      "model": "custom/death_eater_illegal_item"},
		{ "predicate": {"damaged": 0, "damage": 0.8143405889884763},      "model": "custom/illegal_poison"},
		{ "predicate": {"damaged": 0, "damage": 0.8149807938540332},      "model": "custom/cursed_skull"},
		{ "predicate": {"damaged": 0, "damage": 0.8156209987195903},      "model": "custom/ravenclawstatue"},
		{ "predicate": {"damaged": 0, "damage": 0.8162612035851472},      "model": "creatures/flobberworm"},
		{ "predicate": {"damaged": 0, "damage": 0.8169014084507042},      "model": "gameplay_element/fluxweed/fluxweed_bare"},
		{ "predicate": {"damaged": 0, "damage": 0.8175416133162612},      "model": "gameplay_element/fluxweed/fluxweed"},
		{ "predicate": {"damaged": 0, "damage": 0.8181818181818181},      "model": "custom/grimmauld_place/leaves"},
		{ "predicate": {"damaged": 0, "damage": 0.8188220230473752},      "model": "custom/basalisk/fang"},
		{ "predicate": {"damaged": 0, "damage": 0.8194622279129321},      "model": "custom/basalisk/skeleton11"},
		{ "predicate": {"damaged": 0, "damage": 0.820102432778489},       "model": "custom/basalisk/skeleton10"},
		{ "predicate": {"damaged": 0, "damage": 0.8207426376440461},      "model": "custom/basalisk/skeleton9"},
		{ "predicate": {"damaged": 0, "damage": 0.821382842509603},       "model": "custom/basalisk/skeleton8"},
		{ "predicate": {"damaged": 0, "damage": 0.82202304737516},        "model": "custom/basalisk/skeleton7"},
		{ "predicate": {"damaged": 0, "damage": 0.822663252240717},       "model": "custom/basalisk/skeleton6"},
		{ "predicate": {"damaged": 0, "damage": 0.823303457106274},       "model": "custom/basalisk/skeleton5"},
		{ "predicate": {"damaged": 0, "damage": 0.823943661971831},       "model": "custom/basalisk/skeleton4"},
		{ "predicate": {"damaged": 0, "damage": 0.8245838668373879},      "model": "custom/basalisk/skeleton3"},
		{ "predicate": {"damaged": 0, "damage": 0.8252240717029449},      "model": "custom/basalisk/skeleton2"},
		{ "predicate": {"damaged": 0, "damage": 0.8258642765685019},      "model": "custom/basalisk/skeleton1"},
		{ "predicate": {"damaged": 0, "damage": 0.8265044814340589},      "model": "custom/spider_eggs/spider_eggs"},
		{ "predicate": {"damaged": 0, "damage": 0.8271446862996158},      "model": "guis/setup/circle"},
		{ "predicate": {"damaged": 0, "damage": 0.8277848911651728},      "model": "custom/stick"},
		{ "predicate": {"damaged": 0, "damage": 0.8284250960307298},      "model": "custom/underwater_plant"},
		{ "predicate": {"damaged": 0, "damage": 0.8290653008962868},      "model": "custom/borgin_and_burkes_hand"},
		{ "predicate": {"damaged": 0, "damage": 0.8297055057618438},      "model": "custom/paintings/pear_painting"},
		{ "predicate": {"damaged": 0, "damage": 0.8303457106274007},      "model": "custom/snow_man/snow_man_2"},
		{ "predicate": {"damaged": 0, "damage": 0.8309859154929577},      "model": "custom/snow_man/unfinished_snowman"},
		{ "predicate": {"damaged": 0, "damage": 0.8316261203585147},      "model": "custom/snow_man/carrot"},
		{ "predicate": {"damaged": 0, "damage": 0.8322663252240716},      "model": "custom/snow_man/stone"},
		{ "predicate": {"damaged": 0, "damage": 0.8329065300896287},      "model": "custom/snow_man/twig"},
		{ "predicate": {"damaged": 0, "damage": 0.8335467349551856},      "model": "custom/blackboard/key_arrow"},
		{ "predicate": {"damaged": 0, "damage": 0.8341869398207427},      "model": "creatures/fawkes"},
		{ "predicate": {"damaged": 0, "damage": 0.8348271446862996},      "model": "custom/plaque/hogs_head"},
		{ "predicate": {"damaged": 0, "damage": 0.8354673495518565},      "model": "custom/blackboard/spike_maze"},
		{ "predicate": {"damaged": 0, "damage": 0.8361075544174136},      "model": "custom/blackboard/sewer_stairs"},
		{ "predicate": {"damaged": 0, "damage": 0.8367477592829705},      "model": "custom/blackboard/arrow"},
		{ "predicate": {"damaged": 0, "damage": 0.8373879641485275},      "model": "guis/hidden"},
		{ "predicate": {"damaged": 0, "damage": 0.8380281690140845},      "model": "creatures/demiguise/demiguise_5"},
		{ "predicate": {"damaged": 0, "damage": 0.8386683738796414},      "model": "creatures/demiguise/demiguise_4"},
		{ "predicate": {"damaged": 0, "damage": 0.8393085787451985},      "model": "creatures/demiguise/demiguise_3"},
		{ "predicate": {"damaged": 0, "damage": 0.8399487836107554},      "model": "creatures/demiguise/demiguise_2"},
		{ "predicate": {"damaged": 0, "damage": 0.8405889884763124},      "model": "creatures/demiguise/demiguise_1"},
		{ "predicate": {"damaged": 0, "damage": 0.8412291933418694},      "model": "gameplay_element/clue"},
		{ "predicate": {"damaged": 0, "damage": 0.8418693982074263},      "model": "gameplay_element/luna_belongings/necklace"},
		{ "predicate": {"damaged": 0, "damage": 0.8425096030729833},      "model": "gameplay_element/luna_belongings/shoe_l"},
		{ "predicate": {"damaged": 0, "damage": 0.8431498079385403},      "model": "gameplay_element/luna_belongings/shoe_r"},
		{ "predicate": {"damaged": 0, "damage": 0.8437900128040973},      "model": "gameplay_element/luna_belongings/sock_l"},
		{ "predicate": {"damaged": 0, "damage": 0.8444302176696542},      "model": "gameplay_element/luna_belongings/sock_r"},
		{ "predicate": {"damaged": 0, "damage": 0.8450704225352113},      "model": "gameplay_element/flying_key2"},
		{ "predicate": {"damaged": 0, "damage": 0.8457106274007682},      "model": "gameplay_element/flying_key1"},
		{ "predicate": {"damaged": 0, "damage": 0.8463508322663252},      "model": "gameplay_element/riddle_potions/7"},
		{ "predicate": {"damaged": 0, "damage": 0.8469910371318822},      "model": "gameplay_element/riddle_potions/6"},
		{ "predicate": {"damaged": 0, "damage": 0.8476312419974391},      "model": "gameplay_element/riddle_potions/5"},
		{ "predicate": {"damaged": 0, "damage": 0.8482714468629962},      "model": "gameplay_element/riddle_potions/4"},
		{ "predicate": {"damaged": 0, "damage": 0.8489116517285531},      "model": "gameplay_element/riddle_potions/3"},
		{ "predicate": {"damaged": 0, "damage": 0.84955185659411},        "model": "gameplay_element/riddle_potions/2"},
		{ "predicate": {"damaged": 0, "damage": 0.8501920614596671},      "model": "gameplay_element/riddle_potions/1"},
		{ "predicate": {"damaged": 0, "damage": 0.850832266325224},       "model": "custom/scroll"},
		{ "predicate": {"damaged": 0, "damage": 0.8514724711907811},      "model": "custom/underground_library_map"},
		{ "predicate": {"damaged": 0, "damage": 0.852112676056338},       "model": "custom/lock"},
		{ "predicate": {"damaged": 0, "damage": 0.8527528809218949},      "model": "custom/key"},
		{ "predicate": {"damaged": 0, "damage": 0.853393085787452},       "model": "custom/scorch_marks"},
		{ "predicate": {"damaged": 0, "damage": 0.8540332906530089},      "model": "custom/golden_skull"},
		{ "predicate": {"damaged": 0, "damage": 0.8546734955185659},      "model": "custom/blackboard/heads_tails"},
		{ "predicate": {"damaged": 0, "damage": 0.8553137003841229},      "model": "custom/blackboard/alohomora_timer"},
		{ "predicate": {"damaged": 0, "damage": 0.8559539052496798},      "model": "custom/blackboard/alohomora"},
		{ "predicate": {"damaged": 0, "damage": 0.8565941101152369},      "model": "custom/blackboard/reset_mirror"},
		{ "predicate": {"damaged": 0, "damage": 0.8572343149807938},      "model": "custom/blackboard/vera_verto_stair_mirror"},
		{ "predicate": {"damaged": 0, "damage": 0.8578745198463508},      "model": "custom/blackboard/vera_verto_mirror"},
		{ "predicate": {"damaged": 0, "damage": 0.8585147247119078},      "model": "custom/blackboard/three_keys"},
		{ "predicate": {"damaged": 0, "damage": 0.8591549295774648},      "model": "custom/blackboard/three_cubes"},
		{ "predicate": {"damaged": 0, "damage": 0.8597951344430217},      "model": "custom/blackboard/cube_maze"},
		{ "predicate": {"damaged": 0, "damage": 0.8604353393085787},      "model": "custom/blackboard/wingardium_leviosa"},
		{ "predicate": {"damaged": 0, "damage": 0.8610755441741357},      "model": "custom/blackboard/vera_verto_stair"},
		{ "predicate": {"damaged": 0, "damage": 0.8617157490396926},      "model": "custom/blackboard/vera_verto_jump"},
		{ "predicate": {"damaged": 0, "damage": 0.8623559539052497},      "model": "custom/blackboard/vera_verto_armour"},
		{ "predicate": {"damaged": 0, "damage": 0.8629961587708066},      "model": "custom/blackboard/vera_verto"},
		{ "predicate": {"damaged": 0, "damage": 0.8636363636363636},      "model": "custom/blackboard/two_cubes"},
		{ "predicate": {"damaged": 0, "damage": 0.8642765685019206},      "model": "custom/blackboard/two"},
		{ "predicate": {"damaged": 0, "damage": 0.8649167733674775},      "model": "custom/blackboard/three"},
		{ "predicate": {"damaged": 0, "damage": 0.8655569782330346},      "model": "custom/blackboard/stupefy"},
		{ "predicate": {"damaged": 0, "damage": 0.8661971830985915},      "model": "custom/blackboard/reset"},
		{ "predicate": {"damaged": 0, "damage": 0.8668373879641484},      "model": "custom/blackboard/one"},
		{ "predicate": {"damaged": 0, "damage": 0.8674775928297055},      "model": "custom/blackboard/lumos_map_7"},
		{ "predicate": {"damaged": 0, "damage": 0.8681177976952624},      "model": "custom/blackboard/lumos_map_6"},
		{ "predicate": {"damaged": 0, "damage": 0.8687580025608195},      "model": "custom/blackboard/lumos_map_5"},
		{ "predicate": {"damaged": 0, "damage": 0.8693982074263764},      "model": "custom/blackboard/lumos_map_4"},
		{ "predicate": {"damaged": 0, "damage": 0.8700384122919333},      "model": "custom/blackboard/lumos_map_3"},
		{ "predicate": {"damaged": 0, "damage": 0.8706786171574904},      "model": "custom/blackboard/lumos_map_2"},
		{ "predicate": {"damaged": 0, "damage": 0.8713188220230473},      "model": "custom/blackboard/lumos_map_1"},
		{ "predicate": {"damaged": 0, "damage": 0.8719590268886043},      "model": "custom/blackboard/lumos"},
		{ "predicate": {"damaged": 0, "damage": 0.8725992317541613},      "model": "custom/blackboard/four_cubes"},
		{ "predicate": {"damaged": 0, "damage": 0.8732394366197183},      "model": "custom/blackboard/expecto_patronum"},
		{ "predicate": {"damaged": 0, "damage": 0.8738796414852753},      "model": "custom/blackboard/cube_arrow"},
		{ "predicate": {"damaged": 0, "damage": 0.8745198463508322},      "model": "custom/blackboard/bombarda_maxima"},
		{ "predicate": {"damaged": 0, "damage": 0.8751600512163892},      "model": "custom/blackboard/apparition_chasm"},
		{ "predicate": {"damaged": 0, "damage": 0.8758002560819462},      "model": "custom/blackboard/apparition"},
		{ "predicate": {"damaged": 0, "damage": 0.8764404609475032},      "model": "custom/blackboard/alohomora_timer_2"},
		{ "predicate": {"damaged": 0, "damage": 0.8770806658130601},      "model": "custom/paintings/fat_lady_door"},
		{ "predicate": {"damaged": 0, "damage": 0.8777208706786171},      "model": "custom/paintings/fat_lady_frame"},
		{ "predicate": {"damaged": 0, "damage": 0.8783610755441741},      "model": "custom/elevator/gate_side_2"},
		{ "predicate": {"damaged": 0, "damage": 0.8790012804097311},      "model": "custom/elevator/gate_top"},
		{ "predicate": {"damaged": 0, "damage": 0.8796414852752881},      "model": "custom/elevator/gate_side"},
		{ "predicate": {"damaged": 0, "damage": 0.880281690140845},       "model": "custom/elevator/gate11"},
		{ "predicate": {"damaged": 0, "damage": 0.8809218950064021},      "model": "custom/elevator/gate10"},
		{ "predicate": {"damaged": 0, "damage": 0.881562099871959},       "model": "custom/elevator/gate9"},
		{ "predicate": {"damaged": 0, "damage": 0.8822023047375159},      "model": "custom/elevator/gate8"},
		{ "predicate": {"damaged": 0, "damage": 0.882842509603073},       "model": "custom/elevator/gate7"},
		{ "predicate": {"damaged": 0, "damage": 0.8834827144686299},      "model": "custom/elevator/gate6"},
		{ "predicate": {"damaged": 0, "damage": 0.8841229193341869},      "model": "custom/elevator/gate5"},
		{ "predicate": {"damaged": 0, "damage": 0.8847631241997439},      "model": "custom/elevator/gate4"},
		{ "predicate": {"damaged": 0, "damage": 0.8854033290653008},      "model": "custom/elevator/gate3"},
		{ "predicate": {"damaged": 0, "damage": 0.8860435339308579},      "model": "custom/elevator/gate2"},
		{ "predicate": {"damaged": 0, "damage": 0.8866837387964148},      "model": "custom/elevator/gate1"},
		{ "predicate": {"damaged": 0, "damage": 0.8873239436619718},      "model": "custom/elevator/gate0"},
		{ "predicate": {"damaged": 0, "damage": 0.8879641485275288},      "model": "custom/phonebooth"},
		{ "predicate": {"damaged": 0, "damage": 0.8886043533930857},      "model": "gameplay_element/spring_pad_transfigure_8"},
		{ "predicate": {"damaged": 0, "damage": 0.8892445582586427},      "model": "gameplay_element/spring_pad_transfigure_7"},
		{ "predicate": {"damaged": 0, "damage": 0.8898847631241997},      "model": "gameplay_element/spring_pad_transfigure_6"},
		{ "predicate": {"damaged": 0, "damage": 0.8905249679897567},      "model": "gameplay_element/spring_pad_transfigure_5"},
		{ "predicate": {"damaged": 0, "damage": 0.8911651728553137},      "model": "gameplay_element/spring_pad_transfigure_4"},
		{ "predicate": {"damaged": 0, "damage": 0.8918053777208707},      "model": "gameplay_element/spring_pad_transfigure_3"},
		{ "predicate": {"damaged": 0, "damage": 0.8924455825864276},      "model": "gameplay_element/spring_pad_transfigure_2"},
		{ "predicate": {"damaged": 0, "damage": 0.8930857874519846},      "model": "gameplay_element/spring_pad_transfigure_1"},
		{ "predicate": {"damaged": 0, "damage": 0.8937259923175416},      "model": "gameplay_element/spring_pad_30"},
		{ "predicate": {"damaged": 0, "damage": 0.8943661971830985},      "model": "gameplay_element/spring_pad_29"},
		{ "predicate": {"damaged": 0, "damage": 0.8950064020486556},      "model": "gameplay_element/spring_pad_28"},
		{ "predicate": {"damaged": 0, "damage": 0.8956466069142125},      "model": "gameplay_element/spring_pad_27"},
		{ "predicate": {"damaged": 0, "damage": 0.8962868117797695},      "model": "gameplay_element/spring_pad_26"},
		{ "predicate": {"damaged": 0, "damage": 0.8969270166453265},      "model": "gameplay_element/spring_pad_25"},
		{ "predicate": {"damaged": 0, "damage": 0.8975672215108834},      "model": "gameplay_element/spring_pad_24"},
		{ "predicate": {"damaged": 0, "damage": 0.8982074263764405},      "model": "gameplay_element/spring_pad_23"},
		{ "predicate": {"damaged": 0, "damage": 0.8988476312419974},      "model": "gameplay_element/spring_pad_22"},
		{ "predicate": {"damaged": 0, "damage": 0.8994878361075543},      "model": "gameplay_element/spring_pad_21"},
		{ "predicate": {"damaged": 0, "damage": 0.9001280409731114},      "model": "gameplay_element/spring_pad_20"},
		{ "predicate": {"damaged": 0, "damage": 0.9007682458386683},      "model": "gameplay_element/spring_pad_19"},
		{ "predicate": {"damaged": 0, "damage": 0.9014084507042253},      "model": "gameplay_element/spring_pad_18"},
		{ "predicate": {"damaged": 0, "damage": 0.9020486555697823},      "model": "gameplay_element/spring_pad_17"},
		{ "predicate": {"damaged": 0, "damage": 0.9026888604353392},      "model": "gameplay_element/spring_pad_16"},
		{ "predicate": {"damaged": 0, "damage": 0.9033290653008963},      "model": "gameplay_element/spring_pad_15"},
		{ "predicate": {"damaged": 0, "damage": 0.9039692701664532},      "model": "gameplay_element/spring_pad_14"},
		{ "predicate": {"damaged": 0, "damage": 0.9046094750320102},      "model": "gameplay_element/spring_pad_13"},
		{ "predicate": {"damaged": 0, "damage": 0.9052496798975672},      "model": "gameplay_element/spring_pad_12"},
		{ "predicate": {"damaged": 0, "damage": 0.9058898847631242},      "model": "gameplay_element/spring_pad_11"},
		{ "predicate": {"damaged": 0, "damage": 0.9065300896286811},      "model": "gameplay_element/spring_pad_10"},
		{ "predicate": {"damaged": 0, "damage": 0.9071702944942381},      "model": "gameplay_element/spring_pad_9"},
		{ "predicate": {"damaged": 0, "damage": 0.9078104993597951},      "model": "gameplay_element/spring_pad_8"},
		{ "predicate": {"damaged": 0, "damage": 0.9084507042253521},      "model": "gameplay_element/spring_pad_7"},
		{ "predicate": {"damaged": 0, "damage": 0.9090909090909091},      "model": "gameplay_element/spring_pad_6"},
		{ "predicate": {"damaged": 0, "damage": 0.909731113956466},       "model": "gameplay_element/spring_pad_5"},
		{ "predicate": {"damaged": 0, "damage": 0.910371318822023},       "model": "gameplay_element/spring_pad_4"},
		{ "predicate": {"damaged": 0, "damage": 0.91101152368758},        "model": "gameplay_element/spring_pad_3"},
		{ "predicate": {"damaged": 0, "damage": 0.9116517285531369},      "model": "gameplay_element/spring_pad_2"},
		{ "predicate": {"damaged": 0, "damage": 0.912291933418694},       "model": "gameplay_element/spring_pad_1"},
		{ "predicate": {"damaged": 0, "damage": 0.9129321382842509},      "model": "gameplay_element/spring_pad_plant"},
		{ "predicate": {"damaged": 0, "damage": 0.913572343149808},       "model": "custom/chamber_of_secrets/door"},
		{ "predicate": {"damaged": 0, "damage": 0.9142125480153649},      "model": "custom/hats/diadem_pickup"},
		{ "predicate": {"damaged": 0, "damage": 0.9148527528809218},      "model": "gameplay_element/magnet_13"},
		{ "predicate": {"damaged": 0, "damage": 0.9154929577464789},      "model": "gameplay_element/magnet_12"},
		{ "predicate": {"damaged": 0, "damage": 0.9161331626120358},      "model": "gameplay_element/magnet_11"},
		{ "predicate": {"damaged": 0, "damage": 0.9167733674775927},      "model": "gameplay_element/magnet_10"},
		{ "predicate": {"damaged": 0, "damage": 0.9174135723431498},      "model": "gameplay_element/magnet_9"},
		{ "predicate": {"damaged": 0, "damage": 0.9180537772087067},      "model": "gameplay_element/magnet_8"},
		{ "predicate": {"damaged": 0, "damage": 0.9186939820742638},      "model": "gameplay_element/magnet_7"},
		{ "predicate": {"damaged": 0, "damage": 0.9193341869398207},      "model": "gameplay_element/magnet_6"},
		{ "predicate": {"damaged": 0, "damage": 0.9199743918053777},      "model": "gameplay_element/magnet_5"},
		{ "predicate": {"damaged": 0, "damage": 0.9206145966709347},      "model": "gameplay_element/magnet_4"},
		{ "predicate": {"damaged": 0, "damage": 0.9212548015364916},      "model": "gameplay_element/magnet_3"},
		{ "predicate": {"damaged": 0, "damage": 0.9218950064020486},      "model": "gameplay_element/magnet_2"},
		{ "predicate": {"damaged": 0, "damage": 0.9225352112676056},      "model": "gameplay_element/magnet_1"},
		{ "predicate": {"damaged": 0, "damage": 0.9231754161331626},      "model": "gameplay_element/magnet_holder"},
		{ "predicate": {"damaged": 0, "damage": 0.9238156209987195},      "model": "gameplay_element/gold_ring"},
		{ "predicate": {"damaged": 0, "damage": 0.9244558258642765},      "model": "custom/paintings/mirror_painting_2"},
		{ "predicate": {"damaged": 0, "damage": 0.9250960307298335},      "model": "custom/paintings/mirror_painting_1"},
		{ "predicate": {"damaged": 0, "damage": 0.9257362355953905},      "model": "custom/radio/gramophone_on_16"},
		{ "predicate": {"damaged": 0, "damage": 0.9263764404609475},      "model": "custom/radio/gramophone_on_15"},
		{ "predicate": {"damaged": 0, "damage": 0.9270166453265044},      "model": "custom/radio/gramophone_on_14"},
		{ "predicate": {"damaged": 0, "damage": 0.9276568501920615},      "model": "custom/radio/gramophone_on_13"},
		{ "predicate": {"damaged": 0, "damage": 0.9282970550576184},      "model": "custom/radio/gramophone_on_12"},
		{ "predicate": {"damaged": 0, "damage": 0.9289372599231753},      "model": "custom/radio/gramophone_on_11"},
		{ "predicate": {"damaged": 0, "damage": 0.9295774647887324},      "model": "custom/radio/gramophone_on_10"},
		{ "predicate": {"damaged": 0, "damage": 0.9302176696542893},      "model": "custom/radio/gramophone_on_9"},
		{ "predicate": {"damaged": 0, "damage": 0.9308578745198464},      "model": "custom/radio/gramophone_on_8"},
		{ "predicate": {"damaged": 0, "damage": 0.9314980793854033},      "model": "custom/radio/gramophone_on_7"},
		{ "predicate": {"damaged": 0, "damage": 0.9321382842509602},      "model": "custom/radio/gramophone_on_6"},
		{ "predicate": {"damaged": 0, "damage": 0.9327784891165173},      "model": "custom/radio/gramophone_on_5"},
		{ "predicate": {"damaged": 0, "damage": 0.9334186939820742},      "model": "custom/radio/gramophone_on_4"},
		{ "predicate": {"damaged": 0, "damage": 0.9340588988476312},      "model": "custom/radio/gramophone_on_3"},
		{ "predicate": {"damaged": 0, "damage": 0.9346991037131882},      "model": "custom/radio/gramophone_on_2"},
		{ "predicate": {"damaged": 0, "damage": 0.9353393085787451},      "model": "custom/radio/gramophone_on_1"},
		{ "predicate": {"damaged": 0, "damage": 0.9359795134443022},      "model": "custom/radio/gramophone_off"},
		{ "predicate": {"damaged": 0, "damage": 0.9366197183098591},      "model": "custom/radio/old_timey_radio"},
		{ "predicate": {"damaged": 0, "damage": 0.9372599231754161},      "model": "custom/grimmauld_place/grimmauld_slice12"},
		{ "predicate": {"damaged": 0, "damage": 0.9379001280409731},      "model": "custom/grimmauld_place/grimmauld_slice11"},
		{ "predicate": {"damaged": 0, "damage": 0.93854033290653},        "model": "custom/grimmauld_place/grimmauld_slice10"},
		{ "predicate": {"damaged": 0, "damage": 0.939180537772087},       "model": "custom/grimmauld_place/grimmauld_slice9"},
		{ "predicate": {"damaged": 0, "damage": 0.939820742637644},       "model": "custom/grimmauld_place/grimmauld_slice8"},
		{ "predicate": {"damaged": 0, "damage": 0.940460947503201},       "model": "custom/grimmauld_place/grimmauld_slice7"},
		{ "predicate": {"damaged": 0, "damage": 0.941101152368758},       "model": "custom/grimmauld_place/grimmauld_slice6"},
		{ "predicate": {"damaged": 0, "damage": 0.941741357234315},       "model": "custom/grimmauld_place/grimmauld_slice5"},
		{ "predicate": {"damaged": 0, "damage": 0.9423815620998719},      "model": "custom/grimmauld_place/grimmauld_slice4"},
		{ "predicate": {"damaged": 0, "damage": 0.9430217669654289},      "model": "custom/grimmauld_place/grimmauld_slice3"},
		{ "predicate": {"damaged": 0, "damage": 0.9436619718309859},      "model": "custom/grimmauld_place/grimmauld_slice2"},
		{ "predicate": {"damaged": 0, "damage": 0.9443021766965428},      "model": "custom/grimmauld_place/grimmauld_slice1"},
		{ "predicate": {"damaged": 0, "damage": 0.9449423815620999},      "model": "custom/grimmauld_place/grimmauld_pavement"},
		{ "predicate": {"damaged": 0, "damage": 0.9455825864276568},      "model": "custom/grimmauld_place/grimmauld3"},
		{ "predicate": {"damaged": 0, "damage": 0.9462227912932137},      "model": "custom/grimmauld_place/grimmauld2"},
		{ "predicate": {"damaged": 0, "damage": 0.9468629961587708},      "model": "custom/grimmauld_place/grimmauld1"},
		{ "predicate": {"damaged": 0, "damage": 0.9475032010243277},      "model": "gameplay_element/weapon/sting"},
		{ "predicate": {"damaged": 0, "damage": 0.9481434058898848},      "model": "gameplay_element/weapon/gryffindor_sword"},
		{ "predicate": {"damaged": 0, "damage": 0.9487836107554417},      "model": "gameplay_element/weapon/fancy_sword"},
		{ "predicate": {"damaged": 0, "damage": 0.9494238156209986},      "model": "gameplay_element/weapon/rusty_sword"},
		{ "predicate": {"damaged": 0, "damage": 0.9500640204865557},      "model": "gameplay_element/weapon/axe"},
		{ "predicate": {"damaged": 0, "damage": 0.9507042253521126},      "model": "gameplay_element/weapon/beaters_bat"},
		{ "predicate": {"damaged": 0, "damage": 0.9513444302176696},      "model": "custom/dumbledore/dumbledorechair"},
		{ "predicate": {"damaged": 0, "damage": 0.9519846350832266},      "model": "custom/dumbledore/dumbledoredesk"},
		{ "predicate": {"damaged": 0, "damage": 0.9526248399487836},      "model": "custom/plaque/plaque_animal_skull"},
		{ "predicate": {"damaged": 0, "damage": 0.9532650448143406},      "model": "custom/plaque/plaque_fish"},
		{ "predicate": {"damaged": 0, "damage": 0.9539052496798975},      "model": "custom/plaque/plaque_deer"},
		{ "predicate": {"damaged": 0, "damage": 0.9545454545454545},      "model": "custom/goblet_silver_transfiguration"},
		{ "predicate": {"damaged": 0, "damage": 0.9551856594110115},      "model": "custom/rising_water"},
		{ "predicate": {"damaged": 0, "damage": 0.9558258642765685},      "model": "custom/writing/lion_tablet_fallen"},
		{ "predicate": {"damaged": 0, "damage": 0.9564660691421254},      "model": "custom/blackboard_door_riddle"},
		{ "predicate": {"damaged": 0, "damage": 0.9571062740076824},      "model": "custom/writing/time_riddle"},
		{ "predicate": {"damaged": 0, "damage": 0.9577464788732394},      "model": "custom/writing/lion"},
		{ "predicate": {"damaged": 0, "damage": 0.9583866837387964},      "model": "custom/writing/death"},
		{ "predicate": {"damaged": 0, "damage": 0.9590268886043534},      "model": "custom/writing/wind"},
		{ "predicate": {"damaged": 0, "damage": 0.9596670934699103},      "model": "custom/writing/water"},
		{ "predicate": {"damaged": 0, "damage": 0.9603072983354674},      "model": "custom/writing/wand"},
		{ "predicate": {"damaged": 0, "damage": 0.9609475032010243},      "model": "custom/writing/time"},
		{ "predicate": {"damaged": 0, "damage": 0.9615877080665812},      "model": "custom/writing/spike_map"},
		{ "predicate": {"damaged": 0, "damage": 0.9622279129321383},      "model": "custom/writing/clean_tablet"},
		{ "predicate": {"damaged": 0, "damage": 0.9628681177976952},      "model": "custom/writing/eagle_tablet"},
		{ "predicate": {"damaged": 0, "damage": 0.9635083226632521},      "model": "custom/writing/badger_tablet"},
		{ "predicate": {"damaged": 0, "damage": 0.9641485275288092},      "model": "custom/writing/snake_tablet"},
		{ "predicate": {"damaged": 0, "damage": 0.9647887323943661},      "model": "custom/writing/lion_tablet"},
		{ "predicate": {"damaged": 0, "damage": 0.9654289372599232},      "model": "custom/blackboard_stupefy_targets"},
		{ "predicate": {"damaged": 0, "damage": 0.9660691421254801},      "model": "custom/blackboard_lumos_map"},
		{ "predicate": {"damaged": 0, "damage": 0.966709346991037},       "model": "custom/blackboard"},
		{ "predicate": {"damaged": 0, "damage": 0.9673495518565941},      "model": "custom/mannequin/mannequin_slytherin270"},
		{ "predicate": {"damaged": 0, "damage": 0.967989756722151},       "model": "custom/mannequin/mannequin_slytherin180"},
		{ "predicate": {"damaged": 0, "damage": 0.968629961587708},       "model": "custom/mannequin/mannequin_slytherin90"},
		{ "predicate": {"damaged": 0, "damage": 0.969270166453265},       "model": "custom/mannequin/mannequin_slytherin0"},
		{ "predicate": {"damaged": 0, "damage": 0.969910371318822},       "model": "custom/mannequin/mannequin_ravenclaw270"},
		{ "predicate": {"damaged": 0, "damage": 0.970550576184379},       "model": "custom/mannequin/mannequin_ravenclaw180"},
		{ "predicate": {"damaged": 0, "damage": 0.971190781049936},       "model": "custom/mannequin/mannequin_ravenclaw90"},
		{ "predicate": {"damaged": 0, "damage": 0.9718309859154929},      "model": "custom/mannequin/mannequin_ravenclaw0"},
		{ "predicate": {"damaged": 0, "damage": 0.9724711907810499},      "model": "custom/mannequin/mannequin_hufflepuff270"},
		{ "predicate": {"damaged": 0, "damage": 0.9731113956466069},      "model": "custom/mannequin/mannequin_hufflepuff180"},
		{ "predicate": {"damaged": 0, "damage": 0.9737516005121638},      "model": "custom/mannequin/mannequin_hufflepuff90"},
		{ "predicate": {"damaged": 0, "damage": 0.9743918053777209},      "model": "custom/mannequin/mannequin_hufflepuff0"},
		{ "predicate": {"damaged": 0, "damage": 0.9750320102432778},      "model": "custom/mannequin/mannequin_gryffindor270"},
		{ "predicate": {"damaged": 0, "damage": 0.9756722151088348},      "model": "custom/mannequin/mannequin_gryffindor180"},
		{ "predicate": {"damaged": 0, "damage": 0.9763124199743918},      "model": "custom/mannequin/mannequin_gryffindor90"},
		{ "predicate": {"damaged": 0, "damage": 0.9769526248399487},      "model": "custom/mannequin/mannequin_gryffindor0"},
		{ "predicate": {"damaged": 0, "damage": 0.9775928297055058},      "model": "custom/mannequin/mannequin315"},
		{ "predicate": {"damaged": 0, "damage": 0.9782330345710627},      "model": "custom/mannequin/mannequin270"},
		{ "predicate": {"damaged": 0, "damage": 0.9788732394366196},      "model": "custom/mannequin/mannequin225"},
		{ "predicate": {"damaged": 0, "damage": 0.9795134443021767},      "model": "custom/mannequin/mannequin180"},
		{ "predicate": {"damaged": 0, "damage": 0.9801536491677336},      "model": "custom/mannequin/mannequin135"},
		{ "predicate": {"damaged": 0, "damage": 0.9807938540332907},      "model": "custom/mannequin/mannequin90"},
		{ "predicate": {"damaged": 0, "damage": 0.9814340588988476},      "model": "custom/mannequin/mannequin45"},
		{ "predicate": {"damaged": 0, "damage": 0.9820742637644045},      "model": "custom/mannequin/mannequin0"},
		{ "predicate": {"damaged": 0, "damage": 0.9827144686299616},      "model": "custom/signs/weasley_hat"},
		{ "predicate": {"damaged": 0, "damage": 0.9833546734955185},      "model": "custom/small_boat_6"},
		{ "predicate": {"damaged": 0, "damage": 0.9839948783610755},      "model": "custom/small_boat_5"},
		{ "predicate": {"damaged": 0, "damage": 0.9846350832266325},      "model": "custom/small_boat_4"},
		{ "predicate": {"damaged": 0, "damage": 0.9852752880921894},      "model": "custom/small_boat_3"},
		{ "predicate": {"damaged": 0, "damage": 0.9859154929577464},      "model": "custom/small_boat_2"},
		{ "predicate": {"damaged": 0, "damage": 0.9865556978233034},      "model": "custom/small_boat_hagrid"},
		{ "predicate": {"damaged": 0, "damage": 0.9871959026888604},      "model": "custom/small_boat"},
		{ "predicate": {"damaged": 0, "damage": 0.9878361075544174},      "model": "custom/flat_hogwarts"},
		{ "predicate": {"damaged": 0, "damage": 0.9884763124199744},      "model": "custom/statues/knight270"},
		{ "predicate": {"damaged": 0, "damage": 0.9891165172855313},      "model": "custom/statues/knight180"},
		{ "predicate": {"damaged": 0, "damage": 0.9897567221510883},      "model": "custom/statues/knight90"},
		{ "predicate": {"damaged": 0, "damage": 0.9903969270166453},      "model": "custom/statues/knight0"},
		{ "predicate": {"damaged": 0, "damage": 0.9910371318822022},      "model": "custom/statues/gold_owl"},
		{ "predicate": {"damaged": 0, "damage": 0.9916773367477593},      "model": "custom/statues/pig_statue270"},
		{ "predicate": {"damaged": 0, "damage": 0.9923175416133162},      "model": "custom/statues/pig_statue180"},
		{ "predicate": {"damaged": 0, "damage": 0.9929577464788732},      "model": "custom/statues/pig_statue90"},
		{ "predicate": {"damaged": 0, "damage": 0.9935979513444302},      "model": "custom/statues/pig_statue0"},
		{ "predicate": {"damaged": 0, "damage": 0.9942381562099871},      "model": "custom/signs/weasley_arm_2"},
		{ "predicate": {"damaged": 0, "damage": 0.9948783610755442},      "model": "custom/signs/weasley_arm_1"},
		{ "predicate": {"damaged": 0, "damage": 0.9955185659411011},      "model": "custom/skeleton_stand"},
		{ "predicate": {"damaged": 0, "damage": 0.9967989756722151},      "model": "custom/mirror_broken2"},
		{ "predicate": {"damaged": 0, "damage": 0.997439180537772},       "model": "custom/mirror"},
		{ "predicate": {"damaged": 0, "damage": 0.9980793854033291},      "model": "custom/skeleton"},
		{ "predicate": {"damaged": 0, "damage": 0.999359795134443},       "model": "item/armor_stand_models/knight"},
		{ "predicate": {"damaged": 1, "damage": 0},                       "model": "item/diamond_sword"}
	]
}